LICENSE.txt
MANIFEST.in
README.rst
setup.py
async_retrial.egg-info/PKG-INFO
async_retrial.egg-info/SOURCES.txt
async_retrial.egg-info/dependency_links.txt
async_retrial.egg-info/not-zip-safe
async_retrial.egg-info/pbr.json
async_retrial.egg-info/top_level.txt
retrial/__init__.py
retrial/retrial/__init__.py
retrial/retrial/log.py
retrial/retrial/retry.py