Metadata-Version: 1.0
Name: async-retrial
Version: 0.7
Summary: asyncio retrial library
Home-page: https://github.com/nerandell/async_retrial
Author: Ankit Chandawala
Author-email: ankitchandawala@gmail.com
License: UNKNOWN
Platform: UNKNOWN
